tornado_sqlalchemy_login/__init__.py
tornado_sqlalchemy_login/_version.py
tornado_sqlalchemy_login/application.py
tornado_sqlalchemy_login/utils.py
tornado_sqlalchemy_login/assets/static/css/font-awesome.min.css
tornado_sqlalchemy_login/assets/static/fonts/fontawesome-webfont.woff
tornado_sqlalchemy_login/assets/static/fonts/fontawesome-webfont.woff2
tornado_sqlalchemy_login/assets/static/img/fb.svg
tornado_sqlalchemy_login/assets/static/img/in.svg
tornado_sqlalchemy_login/assets/static/img/tw.svg
tornado_sqlalchemy_login/assets/templates/404.html
tornado_sqlalchemy_login/assets/templates/index.html
tornado_sqlalchemy_login/handlers/__init__.py
tornado_sqlalchemy_login/handlers/apikeys.py
tornado_sqlalchemy_login/handlers/base.py
tornado_sqlalchemy_login/handlers/login.py
tornado_sqlalchemy_login/handlers/register.py
tornado_sqlalchemy_login/sqla/__init__.py
tornado_sqlalchemy_login/sqla/fixtures.py
tornado_sqlalchemy_login/sqla/models.py
tornado_sqlalchemy_login/tests/__init__.py
tornado_sqlalchemy_login/tests/test_all.py
tornado_sqlalchemy_login/tests/test_utils.py
tornado_sqlalchemy_login-0.1.0.dist-info/LICENSE
tornado_sqlalchemy_login-0.1.0.dist-info/METADATA
tornado_sqlalchemy_login-0.1.0.dist-info/WHEEL
tornado_sqlalchemy_login-0.1.0.dist-info/top_level.txt
tornado_sqlalchemy_login-0.1.0.dist-info/RECORD
